setup.py
udacity_distributions/Binomialdistribution.py
udacity_distributions/Gaussiandistribution.py
udacity_distributions/Generaldistribution.py
udacity_distributions/__init__.py
udacity_distributions.egg-info/PKG-INFO
udacity_distributions.egg-info/SOURCES.txt
udacity_distributions.egg-info/dependency_links.txt
udacity_distributions.egg-info/not-zip-safe
udacity_distributions.egg-info/top_level.txt