Metadata-Version: 1.0
Name: udacity-distributions
Version: 0.1
Summary: Gaussian distributions
Home-page: UNKNOWN
Author: Ashish Subedi
Author-email: subediashish35@gmail.com
License: UNKNOWN
Platform: UNKNOWN
